runex/__init__.py
runex/cli.py
runex/core.py
runex/ignore_logic.py
runex/wildmatch.py
runex-0.0.2.dist-info/LICENSE
runex-0.0.2.dist-info/METADATA
runex-0.0.2.dist-info/WHEEL
runex-0.0.2.dist-info/entry_points.txt
runex-0.0.2.dist-info/RECORD
