Metadata-Version: 2.3
Name: runex
Version: 0.0.2
Summary: Generates a textual or json project directory structure representation following git's .gitignore rules
License: MIT
Author: Nicolò Balestrino
Author-email: bluejay.ops@gmail.com
Requires-Python: >=3.13
Classifier: License :: OSI Approved :: MIT License
Classifier: Programming Language :: Python :: 3
Classifier: Programming Language :: Python :: 3.13
Requires-Dist: click (>=8.1.8,<9.0.0)
